pikaur/__init__.py
pikaur/__main__.py
pikaur/alpm.py
pikaur/argparse_extras.py
pikaur/args.py
pikaur/aur.py
pikaur/aur_deps.py
pikaur/build.py
pikaur/config.py
pikaur/conflicts.py
pikaur/exceptions.py
pikaur/filelock.py
pikaur/getpkgbuild_cli.py
pikaur/help_cli.py
pikaur/i18n.py
pikaur/info_cli.py
pikaur/install_cli.py
pikaur/install_info_fetcher.py
pikaur/lock.py
pikaur/logging_extras.py
pikaur/main.py
pikaur/makepkg_config.py
pikaur/news.py
pikaur/os_utils.py
pikaur/pacman.py
pikaur/pacman_i18n.py
pikaur/pikaprint.py
pikaur/pikasay.py
pikaur/pikatypes.py
pikaur/pikspect.py
pikaur/pkg_cache_cli.py
pikaur/print_department.py
pikaur/privilege.py
pikaur/progressbar.py
pikaur/prompt.py
pikaur/provider.py
pikaur/py.typed
pikaur/replacements.py
pikaur/search_cli.py
pikaur/spawn.py
pikaur/srcinfo.py
pikaur/updates.py
pikaur/urllib_helper.py
pikaur/version.py
pikaur/extras/__init__.py
pikaur/extras/dep_tree.py
pikaur-1.33.2.dist-info/METADATA
pikaur-1.33.2.dist-info/WHEEL
pikaur-1.33.2.dist-info/entry_points.txt
pikaur-1.33.2.dist-info/licenses/LICENSE
pikaur-1.33.2.dist-info/RECORD
