Metadata-Version: 2.4
Name: pikaur
Version: 1.33.2
Summary: AUR helper with minimal dependencies
Project-URL: repository, https://github.com/actionless/pikaur
Author-email: Yauhen Kirylau <actionless-DOT-loveless-PLUS-aur-AT-gmail-MF-com@anti.spam>
License-File: LICENSE
Keywords: arch,aur,helper,linux
Classifier: Development Status :: 5 - Production/Stable
Classifier: Environment :: Console
Classifier: Intended Audience :: Developers
Classifier: Intended Audience :: End Users/Desktop
Classifier: Intended Audience :: Information Technology
Classifier: Intended Audience :: Other Audience
Classifier: Intended Audience :: System Administrators
Classifier: License :: OSI Approved :: GNU General Public License v3 (GPLv3)
Classifier: Operating System :: POSIX :: Linux
Classifier: Programming Language :: Python :: 3.11
Classifier: Topic :: Software Development :: Build Tools
Classifier: Topic :: System :: Archiving :: Packaging
Classifier: Topic :: System :: Installation/Setup
Classifier: Topic :: Utilities
Requires-Python: >=3.12
Requires-Dist: pyalpm
